[
    {
        "Title": "青莲一页是什么？",
        "Content": ["青莲一页是一个阅读小程序。"]
    },
    {
        "Title": "如何搜索书籍？",
        "Content": ["打开书架页面点击搜索即可。"]
    },
    {
        "Title": "如何设置背景颜色和字号等？",
        "Content": ["请在小说阅读页面点击中心区域，即可自动弹出设置及章节选择。"]
    },
    {
        "Title": "偶尔无法加载不出来内容或提示错误怎么解决？",
        "Content": ["1.加载不出来一般是服务器更新导致，这种情况你重新进入如还是无法看小说，你稍等几分钟或者联系客服反馈解决问题。","2.提示您请求错误只需要退出小程序重新进入即可正常访问。"]
    },
    {
        "Title": "有BUG或产品意见如何反馈？",
        "Content": ["打开【我的】”页面，然后点击【意见反馈】选择反馈类型，我们收到您的建议后如果采纳将会给予反馈者一定的红包奖励，谢谢你们的支持！"]
    }
]